{
"type": "FeatureCollection",
"crs": { "type": "name", "properties": { "name": "urn:ogc:def:crs:OGC:1.3:CRS84" } },
"features": [
{ "type": "Feature", "properties": { "Device_ID": 13010, "Start": "01/01/2022", "End": "16/06/2022" }, "geometry": { "type": "Point", "coordinates": [ 5.046104146, 47.23921582 ] } },
{ "type": "Feature", "properties": { "Device_ID": 13011, "Start": "01/01/2022", "End": "16/06/2022" }, "geometry": { "type": "Point", "coordinates": [ 5.033761963, 47.32524852 ] } },
{ "type": "Feature", "properties": { "Device_ID": 13012, "Start": "01/01/2022", "End": "16/06/2022" }, "geometry": { "type": "Point", "coordinates": [ 5.051834028, 47.27257554 ] } },
{ "type": "Feature", "properties": { "Device_ID": 13013, "Start": "01/01/2022", "End": "16/06/2022" }, "geometry": { "type": "Point", "coordinates": [ 5.053558851, 47.28438358 ] } },
{ "type": "Feature", "properties": { "Device_ID": 13014, "Start": "01/01/2022", "End": "16/06/2022" }, "geometry": { "type": "Point", "coordinates": [ 5.03001386, 47.29986124 ] } },
{ "type": "Feature", "properties": { "Device_ID": 13015, "Start": "01/01/2022", "End": "16/06/2022" }, "geometry": { "type": "Point", "coordinates": [ 5.051030176, 47.24271594 ] } },
{ "type": "Feature", "properties": { "Device_ID": 13016, "Start": "01/01/2022", "End": "30/04/2022" }, "geometry": { "type": "Point", "coordinates": [ 4.993090012, 47.30114935 ] } },
{ "type": "Feature", "properties": { "Device_ID": 13016, "Start": "01/05/2022", "End": "16/06/2022" }, "geometry": { "type": "Point", "coordinates": [ 4.993356696, 47.27759682 ] } },
{ "type": "Feature", "properties": { "Device_ID": 13017, "Start": "01/01/2022", "End": "16/06/2022" }, "geometry": { "type": "Point", "coordinates": [ 5.012264553, 47.25974511 ] } },
{ "type": "Feature", "properties": { "Device_ID": 13018, "Start": "01/01/2022", "End": "16/06/2022" }, "geometry": { "type": "Point", "coordinates": [ 5.04527377, 47.25805412 ] } },
{ "type": "Feature", "properties": { "Device_ID": 13019, "Start": "01/01/2022", "End": "16/06/2022" }, "geometry": { "type": "Point", "coordinates": [ 5.007905783, 47.25164672 ] } },
{ "type": "Feature", "properties": { "Device_ID": 13020, "Start": "01/01/2022", "End": "16/06/2022" }, "geometry": { "type": "Point", "coordinates": [ 4.98967875, 47.27088684 ] } }
]
}
